[
  { "pl": "dom", "en": "house" },
  { "pl": "samochód", "en": "car" },
  { "pl": "książka", "en": "book" },
  { "pl": "komputer", "en": "computer" },
  { "pl": "język", "en": "language" },
  { "pl": "programowanie", "en": "programming" },
  { "pl": "kawa", "en": "coffee" },
  { "pl": "herbata", "en": "tea" },
  { "pl": "pies", "en": "dog" },
  { "pl": "kot", "en": "cat" },
  { "pl": "dzień", "en": "day" },
  { "pl": "noc", "en": "night" },
  { "pl": "woda", "en": "water" },
  { "pl": "ogień", "en": "fire" },
  { "pl": "słońce", "en": "sun" },
  { "pl": "księżyc", "en": "moon" },
  { "pl": "drzewo", "en": "tree" },
  { "pl": "kwiat", "en": "flower" },
  { "pl": "miłość", "en": "love" },
  { "pl": "miasto", "en": "city" },
  { "pl": "rzeka", "en": "river" },
  { "pl": "góra", "en": "mountain" },
  { "pl": "morze", "en": "sea" },
  { "pl": "chmura", "en": "cloud" },
  { "pl": "szybki", "en": "fast" },
  { "pl": "wolny", "en": "slow" },
  { "pl": "kolor", "en": "color" },
  { "pl": "muzyka", "en": "music" },
  { "pl": "film", "en": "movie" },
  { "pl": "telefon", "en": "phone" },
  { "pl": "samolot", "en": "airplane" },
  { "pl": "autobus", "en": "bus" },
  { "pl": "rower", "en": "bicycle" },
  { "pl": "buty", "en": "shoes" },
  { "pl": "ubranie", "en": "clothing" },
  { "pl": "serce", "en": "heart" },
  { "pl": "umysł", "en": "mind" },
  { "pl": "zdrowie", "en": "health" },
  { "pl": "restauracja", "en": "restaurant" },
  { "pl": "hotel", "en": "hotel" },
  { "pl": "lotnisko", "en": "airport" },
  { "pl": "szkoła", "en": "school" },
  { "pl": "uniwersytet", "en": "university" },
  { "pl": "praca", "en": "job" },
  { "pl": "szczęście", "en": "happiness" },
  { "pl": "smutek", "en": "sadness" },
  { "pl": "zdjęcie", "en": "photo" },
  { "pl": "obraz", "en": "painting" },
  { "pl": "malarz", "en": "painter" },
  { "pl": "muzeum", "en": "museum" },
  { "pl": "kino", "en": "cinema" },
  { "pl": "telewizja", "en": "television" },
  { "pl": "internet", "en": "internet" },
  { "pl": "komunikacja", "en": "communication" },
  { "pl": "motocykl", "en": "motorcycle" },
  { "pl": "pociąg", "en": "train" },
  { "pl": "statek", "en": "ship" },
  { "pl": "kosmos", "en": "space" },
  { "pl": "planeta", "en": "planet" },
  { "pl": "gwiazda", "en": "star" },
  { "pl": "kamień", "en": "stone" },
  { "pl": "piasek", "en": "sand" },
  { "pl": "lód", "en": "ice" },
  { "pl": "deszcz", "en": "rain" },
  { "pl": "śnieg", "en": "snow" },
  { "pl": "wiatr", "en": "wind" },
  { "pl": "ogród", "en": "garden" },
  { "pl": "włosy", "en": "hair" },
  { "pl": "oczy", "en": "eyes" },
  { "pl": "usta", "en": "mouth" },
  { "pl": "nos", "en": "nose" },
  { "pl": "ucho", "en": "ear" },
  { "pl": "ręka", "en": "hand" },
  { "pl": "noga", "en": "leg" },
  { "pl": "seria", "en": "series" },
  { "pl": "film animowany", "en": "animated film" },
  { "pl": "gra", "en": "game" },
  { "pl": "sport", "en": "sport" },
  { "pl": "hobby", "en": "hobby" },
  { "pl": "podróż", "en": "travel" },
  { "pl": "przygoda", "en": "adventure" },
  { "pl": "historia", "en": "history" },
  { "pl": "przyszłość", "en": "future" },
  { "pl": "przeszłość", "en": "past" },
  { "pl": "teraz", "en": "now" },
  { "pl": "tutaj", "en": "here" },
  { "pl": "tam", "en": "there" },
  { "pl": "gdzie", "en": "where" },
  { "pl": "kiedy", "en": "when" },
  { "pl": "dlaczego", "en": "why" },
  { "pl": "czekolada", "en": "chocolate" },
  { "pl": "gitara", "en": "guitar" },
  { "pl": "telewizor", "en": "television" },
  { "pl": "kredka", "en": "crayon" },
  { "pl": "kwadrat", "en": "square" },
  { "pl": "okno", "en": "window" },
  { "pl": "koszulka", "en": "t-shirt" },
  { "pl": "telefon komórkowy", "en": "mobile phone" },
  { "pl": "koszykówka", "en": "basketball" },
  { "pl": "kotlet", "en": "cutlet" },
  { "pl": "strona internetowa", "en": "website" },
  { "pl": "basen", "en": "swimming pool" },
  { "pl": "nauka", "en": "science" },
  { "pl": "pizza", "en": "pizza" },
  { "pl": "dzwonek", "en": "bell" },
  { "pl": "zegar", "en": "clock" },
  { "pl": "latarka", "en": "flashlight" },
  { "pl": "trawa", "en": "grass" },
  { "pl": "szklanka", "en": "glass" },
  { "pl": "klawiatura", "en": "keyboard" },
  { "pl": "chleb", "en": "bread" },
  { "pl": "myśl", "en": "thought" },
  { "pl": "broszura", "en": "booklet" },
  { "pl": "ksiądz", "en": "priest" },
  { "pl": "lampa", "en": "lamp" },
  { "pl": "klucz", "en": "key" },
  { "pl": "krzesło", "en": "chair" },
  { "pl": "ekran", "en": "screen" },
  { "pl": "dźwięk", "en": "sound" },
  { "pl": "kredens", "en": "dresser/sideboard" },
  { "pl": "rachunek", "en": "bill" },
  { "pl": "strona", "en": "page" },
  { "pl": "radio", "en": "radio" },
  { "pl": "telewizja satelitarna", "en": "satellite TV" },
  { "pl": "róża", "en": "rose" },
  { "pl": "piesek", "en": "puppy" },
  { "pl": "zdjęcie", "en": "photo" },
  { "pl": "mapa", "en": "map" },
  { "pl": "skrzynia", "en": "box/chest" },
  { "pl": "spódnica", "en": "skirt" },
  { "pl": "klub", "en": "club" },
  { "pl": "kosmos", "en": "cosmos" },
  { "pl": "królik", "en": "rabbit" },
  { "pl": "niedźwiedź", "en": "bear" },
  { "pl": "jezioro", "en": "lake" },
  { "pl": "statek kosmiczny", "en": "spaceship" },
  { "pl": "głowa", "en": "head" },
  { "pl": "serwetka", "en": "napkin" },
  { "pl": "piórnik", "en": "pencil case" },
  { "pl": "kurtka", "en": "jacket" },
  { "pl": "konsola", "en": "console" },
  { "pl": "pudełko", "en": "box" },
  { "pl": "długopis", "en": "pen" },
  { "pl": "niedziela", "en": "Sunday" },
  { "pl": "piątek", "en": "Friday" },
  { "pl": "środa", "en": "Wednesday" },
  { "pl": "woda mineralna", "en": "mineral water" },
  { "pl": "ogród botaniczny", "en": "botanical garden" },
  { "pl": "kotek", "en": "kitten" },
  { "pl": "telewizor", "en": "television" },
  { "pl": "kalkulator", "en": "calculator" },
  { "pl": "okulary", "en": "glasses" },
  { "pl": "dziecko", "en": "child" },
  { "pl": "prezent", "en": "gift" },
  { "pl": "koncert", "en": "concert" },
  { "pl": "poduszka", "en": "pillow" },
  { "pl": "papier", "en": "paper" },
  { "pl": "domek", "en": "cottage" },
  { "pl": "chusteczka", "en": "tissue" },
  { "pl": "przycisk", "en": "button" },
  { "pl": "ekspres do kawy", "en": "coffee maker" },
  { "pl": "podłoga", "en": "floor" },
  { "pl": "kamera", "en": "camera" },
  { "pl": "bas", "en": "bass" },
  { "pl": "skrzypce", "en": "violin" },
  { "pl": "gitara basowa", "en": "bass guitar" },
  { "pl": "zamek", "en": "castle" },
  { "pl": "telewizja kablowa", "en": "cable TV" },
  { "pl": "kurtyna", "en": "curtain" },
  { "pl": "czapka", "en": "hat" },
  { "pl": "kawałek", "en": "piece" },
  { "pl": "kwadratowy", "en": "square" }
]
